myosotis_researches/__init__.py
myosotis_researches/CcGAN/__init__.py
myosotis_researches/CcGAN/models_128/CcGAN_SAGAN.py
myosotis_researches/CcGAN/models_128/ResNet_class_eval.py
myosotis_researches/CcGAN/models_128/ResNet_embed.py
myosotis_researches/CcGAN/models_128/ResNet_regre_eval.py
myosotis_researches/CcGAN/models_128/__init__.py
myosotis_researches/CcGAN/models_128/autoencoder.py
myosotis_researches/CcGAN/models_128/cGAN_SAGAN.py
myosotis_researches/CcGAN/models_128/cGAN_concat_SAGAN.py
myosotis_researches/CcGAN/models_256/CcGAN_SAGAN.py
myosotis_researches/CcGAN/models_256/ResNet_class_eval.py
myosotis_researches/CcGAN/models_256/ResNet_embed.py
myosotis_researches/CcGAN/models_256/ResNet_regre_eval.py
myosotis_researches/CcGAN/models_256/__init__.py
myosotis_researches/CcGAN/models_256/autoencoder.py
myosotis_researches/CcGAN/models_256/cGAN_SAGAN.py
myosotis_researches/CcGAN/models_256/cGAN_concat_SAGAN.py
myosotis_researches/CcGAN/old/IMGs_dataset.py
myosotis_researches/CcGAN/old/SimpleProgressBar.py
myosotis_researches/CcGAN/old/__init__.py
myosotis_researches/CcGAN/old/opts.py
myosotis_researches/CcGAN/old/train.py
myosotis_researches/CcGAN/train/__init__.py
myosotis_researches/CcGAN/train/train_ccgan.py
myosotis_researches/CcGAN/train/train_cgan.py
myosotis_researches/CcGAN/train/train_cgan_concat.py
myosotis_researches/CcGAN/train/train_net_for_label_embed.py
myosotis_researches/CcGAN/utils/__init__.py
myosotis_researches/CcGAN/utils/concat_image.py
myosotis_researches/CcGAN/utils/dataset.py
myosotis_researches/CcGAN/utils/similarity.py
myosotis_researches/CcGAN/utils/src/style.css
myosotis_researches/CcGAN/utils/src/style.css.map
myosotis_researches/CcGAN/utils/src/style.scss
myosotis_researches/CcGAN/utils/src/template.html
myosotis_researches-0.1.42.dist-info/licenses/LICENSE
myosotis_researches-0.1.42.dist-info/METADATA
myosotis_researches-0.1.42.dist-info/WHEEL
myosotis_researches-0.1.42.dist-info/top_level.txt
myosotis_researches-0.1.42.dist-info/RECORD
